fasttext_shop/FastText_Shop.py
fasttext_shop/TextShop_sklearn.py
fasttext_shop/__init__.py
fasttext_shop/stopwords.txt
fasttext_shop/utils.py
fasttext_shop-0.0.8.dist-info/LICENSE
fasttext_shop-0.0.8.dist-info/METADATA
fasttext_shop-0.0.8.dist-info/WHEEL
fasttext_shop-0.0.8.dist-info/RECORD
