Metadata-Version: 2.1
Name: FastText_Shop
Version: 0.0.8
Summary: FastText_Shop是一个基于FastText和结巴分词的短文本分类工具，特点是高效易用，同时支持中文和英文语料。基本使用方法、灵感来自TextGrocery,并且和TextGrocery基本相同。
Home-page: https://gitee.com/ranvane/fasttext_shop
License: MIT
Author: ranvane
Author-email: ranvane@gmail.com
Requires-Python: >=3.9,<4.0
Classifier: License :: OSI Approved :: MIT License
Classifier: Programming Language :: Python :: 3
Classifier: Programming Language :: Python :: 3.9
Classifier: Programming Language :: Python :: 3.10
Classifier: Programming Language :: Python :: 3.11
Classifier: Programming Language :: Python :: 3.12
Requires-Dist: fasttext (>=0.9.2,<0.10.0)
Requires-Dist: jieba (>=0.42.1,<0.43.0)
Requires-Dist: loguru (>=0.7.2,<0.8.0)
Requires-Dist: numpy (>=1.26.4,<2.0.0)
Project-URL: Repository, https://gitee.com/ranvane/fasttext_shop
